{
  "project_info": {
    "project_number": "400932145794",
    "firebase_url": "https://blogapp-9f57a.firebaseio.com",
    "project_id": "blogapp-9f57a",
    "storage_bucket": "blogapp-9f57a.appspot.com"
  },
  "client": [
    {
      "client_info": {
        "mobilesdk_app_id": "1:400932145794:android:f5d5a3e462eb495480429b",
        "android_client_info": {
          "package_name": "com.example.blogapp"
        }
      },
      "oauth_client": [
        {
          "client_id": "400932145794-4b1gume2o2435h4k784j9jvvot54va59.apps.googleusercontent.com",
          "client_type": 1,
          "android_info": {
            "package_name": "com.example.blogapp",
            "certificate_hash": "4c45c62880cbe766bf8db4210eb507b2cbe870ae"
          }
        },
        {
          "client_id": "400932145794-nrfpaofbpde36bb66bpn3c9bkvaevajc.apps.googleusercontent.com",
          "client_type": 3
        }
      ],
      "api_key": [
        {
          "current_key": "AIzaSyBXSxFtn1UbX45jU7hzB1dhs48dqfhKT6g"
        }
      ],
      "services": {
        "appinvite_service": {
          "other_platform_oauth_client": [
            {
              "client_id": "400932145794-nrfpaofbpde36bb66bpn3c9bkvaevajc.apps.googleusercontent.com",
              "client_type": 3
            }
          ]
        }
      }
    }
  ],
  "configuration_version": "1"
}